ggwave.cpython-311-darwin.so
ggwave_fork-0.4.2.dist-info/METADATA
ggwave_fork-0.4.2.dist-info/WHEEL
ggwave_fork-0.4.2.dist-info/top_level.txt
ggwave_fork-0.4.2.dist-info/RECORD
