Metadata-Version: 2.1
Name: ggwave-fork
Version: 0.4.2
Summary: Tiny data-over-sound library.
Home-page: https://github.com/ggerganov/ggwave
Author: Georgi Gerganov
Author-email: ggerganov@gmail.com
License: MIT
Keywords: data-over-sound fsk ecc serverless pairing qrcode ultrasound
